teleport_core/__init__.py
teleport_core/script_exit.py
teleport_core/store.py
xontrib/teleport.py
xontrib_teleport-0.1.1b0.dist-info/METADATA
xontrib_teleport-0.1.1b0.dist-info/WHEEL
xontrib_teleport-0.1.1b0.dist-info/entry_points.txt
xontrib_teleport-0.1.1b0.dist-info/RECORD
