Metadata-Version: 2.1
Name: xontrib-teleport
Version: 0.1.1b0
Summary: 
Author: Your Name
Author-email: you@example.com
Requires-Python: >=3.10,<4.0
Classifier: Programming Language :: Python :: 3
Classifier: Programming Language :: Python :: 3.10
Classifier: Programming Language :: Python :: 3.11
Classifier: Programming Language :: Python :: 3.12
Classifier: Programming Language :: Python :: 3.13
Requires-Dist: pydantic (>=2.9.2,<3.0.0)
Requires-Dist: rich (>=13.9.4,<14.0.0)
Requires-Dist: xonsh (>=0.18.4,<0.19.0)
